firestore_cli/__init__.py
firestore_cli/fsquery.py
firestore_cli/fsupdate.py
firestore_cli-0.2.2.dist-info/licenses/LICENSE
firestore_cli-0.2.2.dist-info/METADATA
firestore_cli-0.2.2.dist-info/WHEEL
firestore_cli-0.2.2.dist-info/entry_points.txt
firestore_cli-0.2.2.dist-info/top_level.txt
firestore_cli-0.2.2.dist-info/RECORD
