Metadata-Version: 2.4
Name: firestore-cli
Version: 0.2.2
Summary: Command-line tool for querying/updating firestore
Author-email: Charles Parker <charles@parkerfolk.net>
Project-URL: Homepage, https://github.com/cdiddy77/firestore-cli
Classifier: Programming Language :: Python :: 3
Classifier: Operating System :: OS Independent
Requires-Python: >=3.10
License-File: LICENSE
Requires-Dist: firebase-admin
Requires-Dist: click
Dynamic: license-file
